LICENSE
README.md
setup.cfg
setup.py
h2_vulnerability_db.egg-info/PKG-INFO
h2_vulnerability_db.egg-info/SOURCES.txt
h2_vulnerability_db.egg-info/dependency_links.txt
h2_vulnerability_db.egg-info/entry_points.txt
h2_vulnerability_db.egg-info/requires.txt
h2_vulnerability_db.egg-info/top_level.txt
test/__init__.py
test/test_db.py
test/test_npm.py
test/test_source.py
test/test_storage.py
test/test_utils.py
vdb/__init__.py
vdb/cli.py
vdb/lib/__init__.py
vdb/lib/config.py
vdb/lib/db.py
vdb/lib/gha.py
vdb/lib/npm.py
vdb/lib/nvd.py
vdb/lib/osv.py
vdb/lib/storage.py
vdb/lib/utils.py