Metadata-Version: 2.1
Name: h2-vulnerability-db
Version: 2.0.2
Summary: AppThreat's vulnerability database and package search library with a built-in file based storage. OSV, CVE, GitHub, npm are the primary sources of vulnerabilities.
Home-page: https://github.com/appthreat/vulnerability-db
Author: h2 security
Author-email: blue-team@h2security.io
License: UNKNOWN
Platform: UNKNOWN
Classifier: Development Status :: 5 - Production/Stable
Classifier: Intended Audience :: Developers
Classifier: Intended Audience :: System Administrators
Classifier: Topic :: Utilities
Classifier: Topic :: Security
Classifier: Programming Language :: Python :: 3.8
Classifier: Programming Language :: Python :: 3.9
Classifier: License :: OSI Approved :: MIT License
Classifier: Operating System :: OS Independent
Requires-Python: >=3.8
